{
  "hosts": [
    {
      "name": "h1",
      "ip": "10.0.0.1"
    },
    {
      "name": "h2",
      "ip": "10.0.0.2"
    },
    {
      "name": "h3",
      "ip": "10.0.1.1"
    },
    {
      "name": "h4",
      "ip": "10.0.1.2"
    },
    {
      "name": "h5",
      "ip": "10.1.0.1"
    },
    {
      "name": "h6",
      "ip": "10.1.0.2"
    },
    {
      "name": "alto_ser",
      "ip": "10.2.0.0"
    }
  ],
  "switches": [
    {
      "name": "s1",
      "dpid": "00:00:00:00:00:00:00:01"
    },
    {
      "name": "s2",
      "dpid": "00:00:00:00:00:00:00:02"
    },
    {
      "name": "s3",
      "dpid": "00:00:00:00:00:00:00:03"
    },
    {
      "name": "s4",
      "dpid": "00:00:00:00:00:00:00:04"
    }
  ],
  "links": [
    {
      "src": "h1",
      "dst": "s1",
      "bw": 1000,
      "delay": 1
    },
    {
      "src": "h2",
      "dst": "s1",
      "bw": 1000,
      "delay": 1
    },
    {
      "src": "h3",
      "dst": "s2",
      "bw": 1000,
      "delay": 1
    },
    {
      "src": "h4",
      "dst": "s2",
      "bw": 1000,
      "delay": 1
    },
    {
      "src": "h5",
      "dst": "s3",
      "bw": 1000,
      "delay": 1
    },
    {
      "src": "h6",
      "dst": "s3",
      "bw": 1000,
      "delay": 1
    },
    {
      "src": "s1",
      "dst": "s2",
      "bw": 1000,
      "delay": 1
    },
    {
      "src": "s2",
      "dst": "s4",
      "bw": 1000,
      "delay": 1
    },
    {
      "src": "s3",
      "dst": "s4",
      "bw": 1000,
      "delay": 1
    },
    {
      "src": "s4",
      "dst": "alto_ser",
      "bw": 1000,
      "delay": 1
    }
  ]
}
